demo_package_python/__init__.py
demo_package_python/random_rainbow_color.py
demo_package_python/say_hello_world.py
demo_package_python/say_hi.py
demo_package_python-0.0.23.dist-info/METADATA
demo_package_python-0.0.23.dist-info/WHEEL
demo_package_python-0.0.23.dist-info/licenses/LICENSE
demo_package_python-0.0.23.dist-info/RECORD
