Metadata-Version: 2.1
Name: demo_package_python
Version: 0.0.23
Summary: This is a sample package which follows the instructions for publishing a Python package to PyPI.
Project-URL: Homepage, https://gitlab.com/demo-package/demo-package-python
Project-URL: Bug Tracker, https://github.com/demo-package/demo-package-python/~/issues
Author-email: "LJ. Sta. Ana" <lvjhn.mx@gmail.com>
License: Copyright 2022 Levi John Sta. Ana
Classifier: License :: OSI Approved :: MIT License
Classifier: Operating System :: OS Independent
Classifier: Programming Language :: Python :: 3
Requires-Python: >=3.7
Requires-Dist: anyio==3.6.1
Requires-Dist: apturl==0.5.2
Requires-Dist: asgiref==3.5.0
Requires-Dist: backpack==0.1
Requires-Dist: bleach==5.0.1
Requires-Dist: blinker==1.4
Requires-Dist: brotli==1.0.9
Requires-Dist: build==0.8.0
Requires-Dist: catfish==4.16.3
Requires-Dist: certifi==2022.6.15
Requires-Dist: cffi==1.15.1
Requires-Dist: chardet==4.0.0
Requires-Dist: charset-normalizer==2.1.0
Requires-Dist: cleo==0.6.8
Requires-Dist: click==8.0.3
Requires-Dist: colorama==0.4.4
Requires-Dist: command-not-found==0.3
Requires-Dist: commonmark==0.9.1
Requires-Dist: cryptography==37.0.4
Requires-Dist: cupshelpers==1.0
Requires-Dist: dbus-python==1.2.18
Requires-Dist: defer==1.0.6
Requires-Dist: distlib==0.3.4
Requires-Dist: distro-info===1.1build1
Requires-Dist: distro==1.7.0
Requires-Dist: docutils==0.19
Requires-Dist: faker==0.8.18
Requires-Dist: filelock==3.7.1
Requires-Dist: gyp==0.1
Requires-Dist: h11==0.13.0
Requires-Dist: httplib2==0.20.2
Requires-Dist: idna==3.3
Requires-Dist: importlib-metadata==4.12.0
Requires-Dist: inflection==0.3.1
Requires-Dist: jeepney==0.8.0
Requires-Dist: keyring==23.6.0
Requires-Dist: language-selector==0.1
Requires-Dist: launchpadlib==1.10.16
Requires-Dist: lazr-restfulclient==0.14.4
Requires-Dist: lazr-uri==1.0.6
Requires-Dist: lazy-object-proxy==1.7.1
Requires-Dist: lightdm-gtk-greeter-settings==1.2.2
Requires-Dist: macaroonbakery==1.3.1
Requires-Dist: mako==1.1.3
Requires-Dist: markupsafe==2.0.1
Requires-Dist: memory-profiler==0.60.0
Requires-Dist: menulibre==2.2.2
Requires-Dist: more-itertools==8.10.0
Requires-Dist: mugshot==0.4.3
Requires-Dist: mutagen==1.45.1
Requires-Dist: netifaces==0.11.0
Requires-Dist: oauthlib==3.2.0
Requires-Dist: olefile==0.46
Requires-Dist: onboard==1.4.1
Requires-Dist: orator==0.9.9
Requires-Dist: packaging==21.3
Requires-Dist: pastel==0.1.1
Requires-Dist: pendulum==1.5.1
Requires-Dist: pep517==0.12.0
Requires-Dist: pexpect==4.8.0
Requires-Dist: pillow==9.0.1
Requires-Dist: pkginfo==1.8.3
Requires-Dist: platformdirs==2.5.2
Requires-Dist: ply==3.11
Requires-Dist: protobuf==3.12.4
Requires-Dist: psutil==5.9.0
Requires-Dist: ptyprocess==0.7.0
Requires-Dist: pyaml==16.12.2
Requires-Dist: pycairo==1.20.1
Requires-Dist: pycparser==2.21
Requires-Dist: pycryptodomex==3.11.0
Requires-Dist: pycups==2.0.1
Requires-Dist: pygments==2.12.0
Requires-Dist: pygobject==3.42.0
Requires-Dist: pyjwt==2.3.0
Requires-Dist: pylev==1.4.0
Requires-Dist: pymacaroons==0.13.0
Requires-Dist: pynacl==1.5.0
Requires-Dist: pyparsing==3.0.9
Requires-Dist: pyrfc3339==1.1
Requires-Dist: python-apt==2.3.0+ubuntu2
Requires-Dist: python-dateutil==2.8.2
Requires-Dist: python-debian===0.1.43ubuntu1
Requires-Dist: pytz==2022.1
Requires-Dist: pytzdata==2020.1
Requires-Dist: pyxattr==0.7.2
Requires-Dist: pyyaml==5.4.1
Requires-Dist: readme-renderer==35.0
Requires-Dist: reportlab==3.6.8
Requires-Dist: requests-toolbelt==0.9.1
Requires-Dist: requests==2.28.1
Requires-Dist: rfc3986==2.0.0
Requires-Dist: rich==12.4.4
Requires-Dist: screen-resolution-extra==0.0.0
Requires-Dist: secretstorage==3.3.2
Requires-Dist: sgt-launcher==0.2.7
Requires-Dist: simplejson==3.17.6
Requires-Dist: six==1.16.0
Requires-Dist: sniffio==1.2.0
Requires-Dist: starlette==0.20.4
Requires-Dist: systemd-python==234
Requires-Dist: text-unidecode==1.2
Requires-Dist: toml==0.10.2
Requires-Dist: tomli==2.0.1
Requires-Dist: twine==4.0.1
Requires-Dist: tzlocal==1.5.1
Requires-Dist: ubuntu-advantage-tools==27.9
Requires-Dist: ubuntu-drivers-common==0.0.0
Requires-Dist: ufw==0.36.1
Requires-Dist: unattended-upgrades==0.1
Requires-Dist: urllib3==1.26.10
Requires-Dist: uvicorn==0.15.0
Requires-Dist: vboxapi==1.0
Requires-Dist: virtualenv==20.15.1
Requires-Dist: wadllib==1.3.6
Requires-Dist: watchdog==2.1.9
Requires-Dist: webencodings==0.5.1
Requires-Dist: websockets==9.1
Requires-Dist: wrapt==1.14.1
Requires-Dist: wsproto==1.0.0
Requires-Dist: xcffib==0.11.1
Requires-Dist: xkit==0.0.0
Requires-Dist: yt-dlp==2022.4.8
Requires-Dist: zipp==3.8.0
